tests/main.py
unimathutils/__init__.py
unimathutils/linalg/__init__.py
unimathutils/linalg/matrix.py
unimathutils/linalg/vector.py
unimathutils/stats/__init__.py
unimathutils/stats/combimatorics.py
unimathlib_pancake-0.1.0.dist-info/METADATA
unimathlib_pancake-0.1.0.dist-info/WHEEL
unimathlib_pancake-0.1.0.dist-info/top_level.txt
unimathlib_pancake-0.1.0.dist-info/RECORD
