Metadata-Version: 2.4
Name: unimathlib-pancake
Version: 0.1.0
Summary: Учебная библиотека по линейной алгебре и теории вероятностей
Author: Pancakeboy1987
License: MIT
Requires-Python: >=3.9
